Workbook
Name aporte: Planilha2!$D$16
Name dividendos_mensais: Planilha2!$B$20
Name patrimonio: Planilha2!$B$19
Name qtd_anos: Planilha2!$D$17
Name rendimento: Planilha2!$D$12
Name salario: Planilha2!$D$11
Name sugestao: Planilha2!$D$13
Name taxa_mensal: Planilha2!$D$18

Sheet Planilha2
B10: Configurações
B11: Salário | D11: 10000
B12: Rendimento Carteira | D12: 0.01
B13: Sugestão de Investimento | D13: 3000
B15: Investimento Mensal
B16: Quanto investir por mês | D16: 500
B17: Por quantos anos investir | D17: 5
B18: Taxa de retorno mensal | D18: 0.01079
A19: 2 | B19: Patrimônio acumulado | D19: =FV(taxa_mensal,qtd_anos*12,-aporte) -> 41888.457
A20: 5 | B20: Dividendos mensais | D20: =D19*rendimento -> 418.88457
A21: 10
A22: 20 | B22: Cenários | D22: Dividendos
A23: 30 | B23: Quanto em 2 anos | C23: =FV($D$18,$A19*12,-$D$16,) -> 13613.814 | D23: =$C23*rendimento -> 136.13814
B24: Quanto em 5 anos | C24: =FV($D$18,$A20*12,-$D$16,) -> 41888.457 | D24: =$C24*rendimento -> 418.88457
B25: Quanto em 10 anos | C25: =FV($D$18,$A21*12,-$D$16,) -> 121642.11 | D25: =$C25*rendimento -> 1216.4211
B26: Quanto em 20 anos | C26: =FV($D$18,$A22*12,-$D$16,) -> 562599.2 | D26: =$C26*rendimento -> 5625.992
B27: Quanto em 30 anos | C27: =FV($D$18,$A23*12,-$D$16,) -> 2161084.8 | D27: =$C27*rendimento -> 21610.848
B29: Perfil | C29: Conservador
B30: Investimento Mensal | C30: 3000
B32: Tipo de FII | C32: Percentual | D32: Valores
B33: Papel | C33: =VLOOKUP($C$29&"-"&B33,Planilha1!B:E,4,FALSE) -> 0.3 | D33: =aporte*$C33 -> 150
B34: Tijolo | C34: =VLOOKUP($C$29&"-"&B34,Planilha1!B:E,4,FALSE) -> 0.5 | D34: =aporte*$C34 -> 250
B35: Híbridos | C35: =VLOOKUP($C$29&"-"&B35,Planilha1!B:E,4,FALSE) -> 0.1 | D35: =aporte*$C35 -> 50
B36: FOFs | C36: =VLOOKUP($C$29&"-"&B36,Planilha1!B:E,4,FALSE) -> 0.1 | D36: =aporte*$C36 -> 50
B37: Desenvolvimento | C37: =VLOOKUP($C$29&"-"&B37,Planilha1!B:E,4,FALSE) -> 0 | D37: =aporte*$C37 -> 0
B38: Hotelarias | C38: =VLOOKUP($C$29&"-"&B38,Planilha1!B:E,4,FALSE) -> 0 | D38: =aporte*$C38 -> 0
B39: Total: | D39: =SUM(D33:D38) -> 500

Sheet Planilha1
B2: Chave Composta | C2: Perfil | D2: Tipo de FII | E2: %
B3: =C3&"-"&D3 -> Conservador-Papel | C3: Conservador | D3: Papel | E3: 0.3
B4: =C4&"-"&D4 -> Conservador-Tijolo | C4: Conservador | D4: Tijolo | E4: 0.5
B5: =C5&"-"&D5 -> Conservador-Híbridos | C5: Conservador | D5: Híbridos | E5: 0.1
B6: =C6&"-"&D6 -> Conservador-FOFs | C6: Conservador | D6: FOFs | E6: 0.1
B7: =C7&"-"&D7 -> Conservador-Desenvolvimento | C7: Conservador | D7: Desenvolvimento | E7: 0
B8: =C8&"-"&D8 -> Conservador-Hotelarias | C8: Conservador | D8: Hotelarias | E8: 0
B9: =C9&"-"&D9 -> Moderado-Papel | C9: Moderado | D9: Papel | E9: 0.32
B10: =C10&"-"&D10 -> Moderado-Tijolo | C10: Moderado | D10: Tijolo | E10: 0.35
B11: =C11&"-"&D11 -> Moderado-Híbridos | C11: Moderado | D11: Híbridos | E11: 0.08
B12: =C12&"-"&D12 -> Moderado-FOFs | C12: Moderado | D12: FOFs | E12: 0.05
B13: =C13&"-"&D13 -> Moderado-Desenvolvimento | C13: Moderado | D13: Desenvolvimento | E13: 0.1
B14: =C14&"-"&D14 -> Moderado-Hotelarias | C14: Moderado | D14: Hotelarias | E14: 0.1
... B20: =C20&"-"&D20 -> Agressivo-Hotelarias | C20: Agressivo | D20: Hotelarias | E20: 0.1
